wordle/__init__.py
wordle/wordle.py
wordle/wordle_allowed.txt
wordle/wordle_answers.txt
reprdle-1.3.0.dist-info/METADATA
reprdle-1.3.0.dist-info/WHEEL
reprdle-1.3.0.dist-info/top_level.txt
reprdle-1.3.0.dist-info/RECORD
