Metadata-Version: 2.1
Name: reprdle
Version: 1.3.0
Summary: Play wordle in the repl with the power of __repr__!
Home-page: https://github.com/torshepherd/reprdle
Author: Tor Shepherd
License: MIT
Platform: UNKNOWN
Classifier: License :: OSI Approved :: MIT License
Classifier: Programming Language :: Python :: 3
Classifier: Programming Language :: Python :: 3.7
Requires-Dist: colored
